speccy_parser-0.1.0.dist-info/DESCRIPTION.rst
speccy_parser-0.1.0.dist-info/METADATA
speccy_parser-0.1.0.dist-info/RECORD
speccy_parser-0.1.0.dist-info/WHEEL
speccy_parser-0.1.0.dist-info/metadata.json
speccy_parser-0.1.0.dist-info/top_level.txt
speccyparse/__init__.py
speccyparse/parser.py
