Metadata-Version: 2.0
Name: speccy-parser
Version: 0.1.0
Summary: A simple library for parsing a Speccy snapshot
Home-page: https://github.com/linuxdaemon/speccy-parser
Author: linuxdaemon
Author-email: linuxdaemon@snoonet.org
License: MIT
Keywords: speccy parser requests
Platform: UNKNOWN
Classifier: Development Status :: 3 - Alpha
Classifier: License :: OSI Approved :: MIT License
Classifier: Programming Language :: Python :: 3.4
Requires-Python: >=3.4
Requires-Dist: requests
Requires-Dist: bs4
Requires-Dist: lxml
